{"inkVersion":20,"root":[["\n","ev",{"VAR?":"coins"},10,">=","/ev",[{"->":".^.b","c":true},{"b":["\n",{"->":"main"},{"->":"0.8"},null]}],[{"->":".^.b"},{"b":["\n",{"->":"idle"},{"->":"0.8"},null]}],"nop","\n",{"->":"idle"},["done",{"#f":5,"#n":"g-0"}],null],"done",{"idle":["^Dear customer, if you don't have at least 10 coins, you're poor and we don't want trash like you in our store. Go fuck yourself, yes, yes.","\n","end",{"#f":1}],"main":["^Here you go! One brand new phone that works without picking up interference from the rift. Pleasure doing business with you, yes, yes.","\n",{"->":"main2"},{"#f":1}],"main2":["ev",true,"/ev",{"VAR=":"getPhone","re":true},"^You've acquired a new phone! Press I to take it out.","\n","end",{"#f":1}],"global decl":["ev","str","^none","/str",{"VAR=":"monologueMoodString"},"str","^none","/str",{"VAR=":"moodStringPlayer"},false,{"VAR=":"PlayerCheckpoint1"},false,{"VAR=":"RiftMonologue"},false,{"VAR=":"OutroCutscene"},false,{"VAR=":"NanalinCheckpoint1"},false,{"VAR=":"NanalinCheckpoint2"},false,{"VAR=":"moveEdithToPosition2"},"str","^none","/str",{"VAR=":"moodStringEdith"},"str","^none","/str",{"VAR=":"isEdithTalking"},false,{"VAR=":"EdithCheckpoint1"},0,{"VAR=":"coins"},false,{"VAR=":"getPhoneQuest"},false,{"VAR=":"moveNanalinToPosition2"},"str","^none","/str",{"VAR=":"moodStringNanalin"},"str","^none","/str",{"VAR=":"isNanalinTalking"},false,{"VAR=":"GhostCheckpoint1"},false,{"VAR=":"GhostCheckpoint2"},false,{"VAR=":"canGhostInteract"},false,{"VAR=":"moveGhostToPosition2"},"str","^none","/str",{"VAR=":"moodStringGhost"},"str","^none","/str",{"VAR=":"isGhostTalking"},false,{"VAR=":"hasNanalinsBracelet"},false,{"VAR=":"hasAncientPowerCore"},false,{"VAR=":"hasEnergyStone"},false,{"VAR=":"getPhone"},false,{"VAR=":"HectorCheckpoint1"},false,{"VAR=":"HectorCheckpoint2"},false,{"VAR=":"moveHectorToPosition2"},false,{"VAR=":"isHectorTalking"},"str","^none","/str",{"VAR=":"moodStringHector"},"/ev","end",null],"#f":1}],"listDefs":{}}